[
    {   
        "id": 1,
        "module_id": 1,
        "title": "Descubra a dança ou ritmo",
        "img": "https://img.freepik.com/vetores-premium/ilustracao-de-frevo-de-design-plano-desenhado-a-mao_52683-80333.jpg?w=2000",
        "type": "MULT",
        "answers": [
            {
                "id": 1,
                "label": "Frevo",
                "answerIsCorrect": true
            },
            {
                "id": 2,
                "label": "Valsa",
                "answerIsCorrect": false
            },
            {
                "id": 3,
                "label": "Samba",
                "answerIsCorrect": false
            },
            {
                "id": 4,
                "label": "Forró",
                "answerIsCorrect": false
            }
        ]
    },
    {   
        "id": 2,
        "module_id": 1,
        "title": "Qual o nome da figura folclórica?",
        "img": "https://pm1.narvii.com/6600/ef3744e4e8eb12562a9333f2384a2333b5341b49_hq.jpg",
        "type": "MULT",
        "answers": [
            {
                "id": 1,
                "label": "Kurupira",
                "answerIsCorrect": true
            },
            {
                "id": 2,
                "label": "Curupira",
                "answerIsCorrect": false
            },
            {
                "id": 3,
                "label": "Cururu",
                "answerIsCorrect": false
            },
            {
                "id": 4,
                "label": "Qurupira",
                "answerIsCorrect": false
            }
        ]
    },
    {
        "id": 3,
        "module_id": 1,
        "title": "Qual o nome da figura folclórica?",
        "img": "http://pm1.narvii.com/6998/0e3bf796904952e7b2ad29f9baed181905edd20er1-1444-2048v2_uhq.jpg",
        "type": "MULT",
        "answers": [
            {
                "id": 1,
                "label": "Sassi",
                "answerIsCorrect": false
            },
            {
                "id": 2,
                "label": "Sasi",
                "answerIsCorrect": false
            },
            {
                "id": 3,
                "label": "Saci",
                "answerIsCorrect": true
            },
            {
                "id": 4,
                "label": "Chassi",
                "answerIsCorrect": false
            }
        ]
    },
    {
        "id": 4,
        "module_id": 1,
        "title": "Complete as letras que faltam",
        "img": "https://blog.biglar.com.br/wp-content/uploads/2021/10/typical-brazilian-dish-called-feijoada-made-with-black-beans-pork-sausage.jpg",
        "type": "COMPLETE",
        "answers": "feijoada",
        "question": "fei*oa*a"
    },
    {
        "id": 5,
        "module_id": 1,
        "title": "Complete as letras que faltam",
        "img": "https://www.sabornamesa.com.br/media/k2/items/cache/3307717c0fe122dc2ed142f42c77bf35_XL.jpg",
        "type": "COMPLETE",
        "answers": "moqueca",
        "question": "mo*u*c*"
    },
    {
        "id": 6,
        "module_id": 1,
        "title": "Complete as letras que faltam",
        "img": "https://www.politize.com.br/wp-content/uploads/2022/03/CapoeiraEarle.jpg",
        "type": "COMPLETE",
        "answers": "capoeira",
        "question": "c*p*e*r*"
    },
    {
        "id": 7,
        "module_id": 1,
        "title": "Complete as letras que faltam",
        "img": "https://portalprudentino.com.br/imagens/uploads/2019/08/c7fb65796b2db2ea652d6abb58700d5d.jpg",
        "type": "COMPLETE",
        "answers": "samba",
        "question": "s*mb*"
    },
    {
        "id": 8,
        "module_id": 1,
        "title": "Complete as letras que faltam",
        "img": "https://portalaracagi.com.br/wp-content/uploads/2020/07/csm_forro-patrimonio_9193640c86.jpg",
        "type": "COMPLETE",
        "answers": "forró",
        "question": "f***ó"
    },

    {
        "id": 9,
        "module_id": 2,
        "title": "Resolva o seguinte problema",
        "text": "O senhor Thiago tem 400 pés de milho com 3 espigas cada pé. Se tudo ocorrer bem e ele colher todas as espigas de milho boas, quantas espigas ele terá?",
        "type": "CALC",
        "answers": "400,x,3,=,1200",
        "question": "400,x,3,=,*"
    },
    {
        "id": 10,
        "module_id": 2,
        "title": "Resolva o seguinte problema",
        "text": "Dona Hildete vendeu 20 copos de mingau, 30 pedaços de bolo e 5 pastéis na ferinha do bairro hoje. Quantos itens dona Hildete vendeu hoje?",
        "type": "CALC",
        "answers": "20,+,30,+,5,=,55",
        "question": "*,*,30,*,5,=,55"
    },
    {
        "id": 11,
        "module_id": 2,
        "title": "Resolva o seguinte problema",
        "text": "Numa fábrica produz 150 sapatos em 1 dia. Em uma semana quantos sapatos são produzidos pela empresa?",
        "type": "CALC",
        "answers": "(150,x,7),÷,1,=,1050",
        "question": "(150,*,7),÷,*,=,*"
    },
    {
        "id": 12,
        "module_id": 2,
        "title": "Resolva o seguinte problema",
        "text": "Vitória recebeu seu salário de R$ 1000. Na manha seguinte ela pagou R$ 300 de mercado, pagou R$ 38 na conta de luz e R$ 62 na conta de água e R$ 300 de aluguel. Quanto Vitória ainda tem?",
        "type": "CALC",
        "answers": "1000,-,300,-,38,-,62,-,300,=,300",
        "question": "1000,-,*,-,*,-,*,-,300,=,*"
    }
]